terrajinja/cli/__init__.py
terrajinja/cli/__main__.py
terrajinja/cli/parse_args.py
terrajinja/cli/parse_jinja.py
terrajinja/cli/parser.py
terrajinja_cli-0.7.1.dist-info/LICENSE
terrajinja_cli-0.7.1.dist-info/METADATA
terrajinja_cli-0.7.1.dist-info/WHEEL
terrajinja_cli-0.7.1.dist-info/entry_points.txt
terrajinja_cli-0.7.1.dist-info/top_level.txt
terrajinja_cli-0.7.1.dist-info/RECORD
